dvg_pyqt_filelogger.py
dvg_pyqt_filelogger-1.4.0.dist-info/AUTHORS.rst
dvg_pyqt_filelogger-1.4.0.dist-info/LICENSE.txt
dvg_pyqt_filelogger-1.4.0.dist-info/METADATA
dvg_pyqt_filelogger-1.4.0.dist-info/WHEEL
dvg_pyqt_filelogger-1.4.0.dist-info/top_level.txt
dvg_pyqt_filelogger-1.4.0.dist-info/RECORD
