Metadata-Version: 2.1
Name: dvg-pyqt-filelogger
Version: 1.4.0
Summary: PyQt/PySide interface to handle logging data to file particularly well suited for multithreaded programs.
Home-page: https://github.com/Dennis-van-Gils/python-dvg-pyqt-filelogger
Author: Dennis van Gils
Author-email: vangils.dennis@gmail.com
License: MIT
Project-URL: Issue Tracker, https://github.com/Dennis-van-Gils/python-dvg-pyqt-filelogger/issues
Keywords: PyQt5,PyQt6,PySide2,PySide6,log,data,multithread
Classifier: Development Status :: 5 - Production/Stable
Classifier: License :: OSI Approved :: MIT License
Classifier: Intended Audience :: Developers
Classifier: Intended Audience :: Science/Research
Classifier: Operating System :: OS Independent
Classifier: Programming Language :: Python
Classifier: Programming Language :: Python :: 3
Classifier: Topic :: Utilities
Classifier: Topic :: Scientific/Engineering 
Classifier: Topic :: Scientific/Engineering :: Electronic Design Automation (EDA)
Requires-Python: >=3.6
License-File: LICENSE.txt
License-File: AUTHORS.rst
Requires-Dist: numpy <3.0,>=1.15
Requires-Dist: dvg-debug-functions ~=2.5
Requires-Dist: qtpy
